dob/__init__.py
dob/clickux/__init__.py
dob/clickux/_ansitextwrap.py
dob/clickux/add_fact_help_group.py
dob/clickux/aliasable_bunchy_plugin.py
dob/clickux/better_format_usage.py
dob/clickux/better_help_headers.py
dob/clickux/bunchy_group.py
dob/clickux/bunchy_help.py
dob/clickux/cmd_options.py
dob/clickux/cmd_options_search.py
dob/clickux/help_command.py
dob/clickux/help_detect.py
dob/clickux/help_header.py
dob/clickux/help_string_add_fact.py
dob/clickux/help_strings.py
dob/clickux/induct_newbies.py
dob/clickux/plugin_group.py
dob/clickux/post_processor.py
dob/clickux/query_assist.py
dob/cmds_list/__init__.py
dob/cmds_list/activity.py
dob/cmds_list/category.py
dob/cmds_list/fact.py
dob/cmds_list/tag.py
dob/cmds_usage/__init__.py
dob/cmds_usage/activity.py
dob/cmds_usage/category.py
dob/cmds_usage/tag.py
dob/complete.py
dob/config/__init__.py
dob/config/cmds_config.py
dob/config/conf_filename.py
dob/config/envvar_prefix.py
dob/config/init_app_dirs.py
dob/controller.py
dob/copyright.py
dob/demo.py
dob/details.py
dob/dob.py
dob/facts/__init__.py
dob/facts/add_fact.py
dob/facts/cancel_fact.py
dob/facts/echo_fact.py
dob/facts/edit_fact.py
dob/facts/import_facts.py
dob/facts/save_backedup.py
dob/facts/save_confirmed.py
dob/facts/save_confirmer.py
dob/facts/simple_prompts.py
dob/helpers/__init__.py
dob/helpers/path.py
dob/migrate.py
dob/plugins.py
dob/run_cli.py
dob-3.1.1.dist-info/LICENSE
dob-3.1.1.dist-info/METADATA
dob-3.1.1.dist-info/WHEEL
dob-3.1.1.dist-info/entry_points.txt
dob-3.1.1.dist-info/RECORD
